{"cameraMode":{"drawMode":0,"name":"Shaded","section":"Shading Mode"},"sceneLighting":false,"audioPlay":false,"sceneViewState":{"m_AlwaysRefresh":false,"showFog":true,"showSkybox":false,"showFlares":true,"showImageEffects":true,"showParticleSystems":true,"showVisualEffectGraphs":true,"m_FxEnabled":true},"in2DMode":false,"pivot":{"x":-4.438529968261719,"y":1.8783283233642579,"z":1.578413963317871},"rotation":{"x":0.34554174542427065,"y":0.5257399678230286,"z":-0.24642644822597505,"w":0.7372134923934937},"size":0.8660253882408142,"orthographic":false}